seaviz/__init__.py
seaviz/__main__.py
seaviz/__version__.py
seaviz/cli.py
seaviz-0.1.dist-info/DESCRIPTION.rst
seaviz-0.1.dist-info/METADATA
seaviz-0.1.dist-info/RECORD
seaviz-0.1.dist-info/WHEEL
seaviz-0.1.dist-info/entry_points.txt
seaviz-0.1.dist-info/metadata.json
seaviz-0.1.dist-info/top_level.txt
